<?xml version="1.0" encoding="UTF-8"?><record_update table="sys_ux_app_route">
    <sys_ux_app_route action="DELETE">
        <app_config display_value="Emergency Alert - admin">07c21b7651c42010f8776b3ef04afff2</app_config>
        <description/>
        <fields/>
        <icon/>
        <name>loginspike</name>
        <optional_parameters/>
        <order>0</order>
        <parent_macroponent display_value="UXR Portal AppShell">9533bf435b130010b913cbd59b81c7c6</parent_macroponent>
        <parent_macroponent_composition_element_id/>
        <route_type>loginspike</route_type>
        <screen_type display_value="loginspike">95de5fbbdb2c2010a92f5a75dc9619c3</screen_type>
        <sys_class_name>sys_ux_app_route</sys_class_name>
        <sys_created_by>admin</sys_created_by>
        <sys_created_on>2020-11-25 07:42:57</sys_created_on>
        <sys_id>e9de13fbdb2c2010a92f5a75dc961926</sys_id>
        <sys_mod_count>0</sys_mod_count>
        <sys_name>loginspike</sys_name>
        <sys_package display_value="Emergency Alert" source="x_snc_emergency_al">2962137651c42010f8776b3ef04affc3</sys_package>
        <sys_policy/>
        <sys_scope display_value="Emergency Alert">2962137651c42010f8776b3ef04affc3</sys_scope>
        <sys_update_name>sys_ux_app_route_e9de13fbdb2c2010a92f5a75dc961926</sys_update_name>
        <sys_updated_by>admin</sys_updated_by>
        <sys_updated_on>2020-11-25 07:42:57</sys_updated_on>
    </sys_ux_app_route>
    <sys_update_version action="INSERT_OR_UPDATE">
        <action>DELETE</action>
        <application display_value="Emergency Alert">2962137651c42010f8776b3ef04affc3</application>
        <file_path/>
        <instance_id>77918959db406c50c6e711f84896196b</instance_id>
        <instance_name>emergencydevportal</instance_name>
        <name>sys_ux_app_route_e9de13fbdb2c2010a92f5a75dc961926</name>
        <payload><![CDATA[<?xml version="1.0" encoding="UTF-8"?><record_update table="sys_ux_app_route"><sys_ux_app_route action="INSERT_OR_UPDATE"><app_config display_value="Emergency Alert - admin">07c21b7651c42010f8776b3ef04afff2</app_config><description/><fields/><icon/><name>loginspike</name><optional_parameters/><order>0</order><parent_macroponent display_value="UXR Portal AppShell">9533bf435b130010b913cbd59b81c7c6</parent_macroponent><parent_macroponent_composition_element_id/><route_type>loginspike</route_type><screen_type display_value="loginspike">95de5fbbdb2c2010a92f5a75dc9619c3</screen_type><sys_class_name>sys_ux_app_route</sys_class_name><sys_created_by>admin</sys_created_by><sys_created_on>2020-11-25 07:42:57</sys_created_on><sys_id>e9de13fbdb2c2010a92f5a75dc961926</sys_id><sys_mod_count>0</sys_mod_count><sys_name>loginspike</sys_name><sys_package display_value="Emergency Alert" source="x_snc_emergency_al">2962137651c42010f8776b3ef04affc3</sys_package><sys_policy/><sys_scope display_value="Emergency Alert">2962137651c42010f8776b3ef04affc3</sys_scope><sys_update_name>sys_ux_app_route_e9de13fbdb2c2010a92f5a75dc961926</sys_update_name><sys_updated_by>admin</sys_updated_by><sys_updated_on>2020-11-25 07:42:57</sys_updated_on></sys_ux_app_route></record_update>]]></payload>
        <payload_hash>-865777716</payload_hash>
        <record_name>loginspike</record_name>
        <reverted_from/>
        <source>91ed6751db1820105de6f9751d961952</source>
        <source_table>sys_update_set</source_table>
        <state>previous</state>
        <sys_created_by>admin</sys_created_by>
        <sys_created_on>2020-11-25 07:42:57</sys_created_on>
        <sys_id>21de13fbdb2c2010a92f5a75dc961929</sys_id>
        <sys_mod_count>0</sys_mod_count>
        <sys_recorded_at>175fe5afde80000001</sys_recorded_at>
        <sys_updated_by>admin</sys_updated_by>
        <sys_updated_on>2020-11-25 07:42:57</sys_updated_on>
        <type>UX App Route</type>
        <update_guid>69de13fb1b2c201050515137d94bf328</update_guid>
        <update_guid_history>69de13fb1b2c201050515137d94bf328:-865777716</update_guid_history>
    </sys_update_version>
    <sys_metadata_delete action="INSERT_OR_UPDATE">
        <sys_audit_delete/>
        <sys_class_name>sys_metadata_delete</sys_class_name>
        <sys_created_by>admin</sys_created_by>
        <sys_created_on>2020-11-25 09:36:27</sys_created_on>
        <sys_db_object display_value="" name="sys_ux_app_route">sys_ux_app_route</sys_db_object>
        <sys_id>11909dcd4009476d95d3788893ceb8a1</sys_id>
        <sys_metadata>e9de13fbdb2c2010a92f5a75dc961926</sys_metadata>
        <sys_mod_count>0</sys_mod_count>
        <sys_name>loginspike</sys_name>
        <sys_package display_value="Emergency Alert" source="x_snc_emergency_al">2962137651c42010f8776b3ef04affc3</sys_package>
        <sys_parent/>
        <sys_policy/>
        <sys_scope display_value="Emergency Alert">2962137651c42010f8776b3ef04affc3</sys_scope>
        <sys_scope_delete display_value="">357fd6ace0af4fe48adcb3448b39e990</sys_scope_delete>
        <sys_update_name>sys_ux_app_route_e9de13fbdb2c2010a92f5a75dc961926</sys_update_name>
        <sys_update_version display_value="sys_ux_app_route_e9de13fbdb2c2010a92f5a75dc961926">21de13fbdb2c2010a92f5a75dc961929</sys_update_version>
        <sys_updated_by>admin</sys_updated_by>
        <sys_updated_on>2020-11-25 09:36:27</sys_updated_on>
    </sys_metadata_delete>
</record_update>
